{
  "id": "MCA-2701",
  "parent_id": "MCA-2700",
  "title": "Requesting the ›has-prime-image‹ relationship when there exists none",
  "gherkin": "Given there exists a \"MAGAZINE\" \"Top Gear\"\nAnd there exists NO \"has prime image\" relationship for \"Top Gear\"\nWhen the user requests the \"has prime image\" relationship for \"Top Gear\"\nThen the request should be confirmed with status code 200\nBut the response should return an empty body",
  "labels": [],
  "created_at": "2026-02-24T17:23:22.193+0100",
  "updated_at": "2026-02-24T17:23:25.687+0100"
}
