{
  "id": "MCA-2659",
  "parent_id": "MCA-202",
  "title": "Create MAGAZINE-has-image Relationship",
  "user_story": "",
  "description": "* The relationship ›has-image‹ is created when the provided IDs of the MAGAZINE and IMAGE are valid. -> Status Code \\`201\\`\n* A successful request returns the ID of the created relationship, the relationship name and the relationship partner.\n* Requests with invalid IDs are rejected. This can happen when there exist no nodes with the given IDs or when those nodes are from the wrong type. -> Status Code \\`404\\`\n* The same ›has-image‹ relationship between the same nodes can only be created once. Attempts to recreate them will be ignored. -> Status Code \\`304\\`\n* Each MAGAZINE can be in a ›has-image‹ relationship with multiple IMAGES\n",
  "api_verb": "POST",
  "api_path": "/magazines/<magazine-id>/has-image/<image-id>",
  "response_options": [
    "201",
    "304",
    "404"
  ],
  "release_versions": [
    "0.28.0"
  ],
  "created_at": "2026-02-24T17:16:11.684+0100",
  "updated_at": "2026-03-02T13:36:31.599+0100"
}
