{
  "id": "MCA-4677",
  "parent_id": "MCA-4674",
  "title": "Trying to create a ›has-video‹ relationship where both IDs are invalid",
  "gherkin": "Given \"GAMING PLATFORM\" \"Xbox\" does NOT exist\nAnd \"VIDEO\" \"Promo Video\" does NOT exist\nWhen the user creates a \"has-video\" relationship between \"Xbox\" and \"Promo Video\"\nThen the request should be rejected with status code 404",
  "labels": [
    "implemented"
  ],
  "created_at": "2026-03-30T17:36:51.682+0200",
  "updated_at": "2026-04-01T11:57:25.049+0200"
}
