{
  "id": "MCA-426",
  "parent_id": "MCA-406",
  "title": "Trying to delete a ›has-prime-image‹ relationship where both IDs are invalid",
  "gherkin": "Given \"CAR MODEL\" \"Mondeo\" does NOT exist\nAnd \"IMAGE\" \"front-left.jpg\" does NOT exist\nWhen the user deletes the \"has prime image\" relationship between \"Mondeo\" and \"front-left.jpg\"\nThen the request should be rejected with status code 404",
  "labels": [
    "implemented"
  ],
  "created_at": "2025-08-24T18:30:12.850+0200",
  "updated_at": "2025-10-13T15:24:04.709+0200"
}
