{
  "id": "MCA-2309",
  "parent_id": "MCA-2298",
  "title": "Read-only properties cannot be overridden by the user when creating a RACING GAME",
  "description": "Read-only properties are for example \\`ID\\`, \\`created\\_at\\` and \\`updated\\_at\\`. Analog to unknown properties, those fields will be ignored. They will not be processed and there will be no info, warning or error that they were skipped.\n",
  "release_version": "0.27.0",
  "created_at": "2026-02-09T12:42:56.178+0100",
  "updated_at": "2026-02-10T13:39:19.146+0100"
}
