{
  "id": "MCA-964",
  "parent_id": "MCA-229",
  "title": "Hard Delete TRACK LAYOUT Node",
  "user_story": "As an API contributor\nI want to be able to delete a TRACK LAYOUT\nSo I can clean up bad data, test data or redundant data\n",
  "description": "* The selected TRACK LAYOUT node is deleted when it actually exists. -> Status Code \\`204\\`\n* All attached relationships are also deleted when the node is deleted.\n* Requests with invalid ID are rejected. This case can happen when there exists no node with that ID or when the node is not from type TRACK LAYOUT. -> Status Code \\`404\\`\n",
  "api_verb": "DELETE",
  "api_path": "/track-layouts/<track-layout-id>",
  "response_options": [
    "204",
    "404"
  ],
  "release_versions": [
    "0.23.0"
  ],
  "created_at": "2025-10-20T18:51:40.883+0200",
  "updated_at": "2025-10-21T10:59:50.766+0200"
}
