{
  "id": "MCA-3228",
  "parent_id": "MCA-3227",
  "title": "Trying to fetch the ›reviewed-by-magazine-issue-with-rating‹ relationships with an invalid CAR MODEL VARIANT ID",
  "gherkin": "Given \"CAR MODEL VARIANT\" \"McLaren 750S\" does NOT exist\nWhen the user requests all \"reviewed by magazine issue with rating\" relationships for \"McLaren 750S\"\nThen the request should be rejected with status code 404",
  "labels": [
    "implemented"
  ],
  "created_at": "2026-03-05T19:41:33.209+0100",
  "updated_at": "2026-03-06T13:09:47.904+0100"
}
