{
  "id": "MCA-31",
  "parent_id": "MCA-27",
  "title": "Invalid properties should be ignored when creating a CAR MODEL",
  "gherkin": "When the user creates a \"CAR MODEL\" \"Test Car\" with the following data\n  | key         | value    | datatype |\n  | name        | Test Car | string   |\n  | generattion | 3        | number   |\n  | code        | ABC      | string   |\nThen the following keys in the response object should be of value null\n  | key           |\n  | generation    |\n  | internal_code |\nAnd the response should NOT contain the following keys\n  | key         |\n  | generattion |\n  | code        |",
  "labels": [
    "implemented"
  ],
  "created_at": "2025-05-04T13:05:58.825+0200",
  "updated_at": "2025-05-08T11:50:54.683+0200"
}
